LICENSE.txt
MANIFEST.in
README.md
setup.py
mygengo/__init__.py
mygengo/mockdb.py
mygengo/mygengo.py
mygengo/test_keys.py
mygengo/test_keys_example.py
mygengo/tests.py
mygengo.egg-info/PKG-INFO
mygengo.egg-info/SOURCES.txt
mygengo.egg-info/dependency_links.txt
mygengo.egg-info/requires.txt
mygengo.egg-info/top_level.txt