Metadata-Version: 1.0
Name: mygengo
Version: 1.3.2
Summary: Official Python library for interfacing with the MyGengo API.
Home-page: http://github.com/ryanmcgrath/mygengo/tree/master
Author: Ryan McGrath
Author-email: ryan@venodesigns.net
License: LGPL License
Keywords: mygengo translation language api japanese english
Platform: UNKNOWN
Classifier: Development Status :: 4 - Beta
Classifier: Intended Audience :: Developers
Classifier: License :: OSI Approved :: MIT License
Classifier: Topic :: Software Development :: Libraries :: Python Modules
Classifier: Topic :: Communications :: Chat
Classifier: Topic :: Internet
